pysyriatel-2.1.1.dist-info/licenses/LICENSE
syriatel/__init__.py
syriatel/client.py
syriatel/exceptions.py
syriatel/models.py
pysyriatel-2.1.1.dist-info/METADATA
pysyriatel-2.1.1.dist-info/WHEEL
pysyriatel-2.1.1.dist-info/top_level.txt
pysyriatel-2.1.1.dist-info/RECORD
