Metadata-Version: 2.4
Name: PySyriatel
Version: 2.1.1
Summary: Python client for Syriatel API
Author-email: melchersman <melchersman@gmail.com>
License: MIT
Project-URL: Homepage, https://github.com/melchersman/PySyriatel
Project-URL: Documentation, https://api.melchersman.com/syr-cash/api-docs
Project-URL: Repository, https://github.com/melchersman/PySyriatel
Project-URL: Issues, https://github.com/melchersman/PySyriatel/issues
Keywords: syriatel,cash,api,syria,payment,mobile,money
Classifier: Development Status :: 4 - Beta
Classifier: Intended Audience :: Developers
Classifier: License :: OSI Approved :: MIT License
Classifier: Operating System :: OS Independent
Classifier: Programming Language :: Python :: 3
Classifier: Programming Language :: Python :: 3.7
Classifier: Programming Language :: Python :: 3.8
Classifier: Programming Language :: Python :: 3.9
Classifier: Programming Language :: Python :: 3.10
Classifier: Programming Language :: Python :: 3.11
Classifier: Topic :: Software Development :: Libraries :: Python Modules
Classifier: Topic :: Internet :: WWW/HTTP :: Dynamic Content
Requires-Python: >=3.7
License-File: LICENSE
Requires-Dist: aiohttp>=3.8.0
Requires-Dist: requests>=2.28.0
Dynamic: license-file
